{"1": "Dr. Sasangan Ramanathan", "2": "Dr. Krishnashree Achuthan", "3": "Dr. Mahadevan S.", "4": "Dr. Balakrishnan Shankar", "5": "Dr. Rakesh S. G.", "6": "Dr. Shantanu Bhowmik", "7": "Dr. Jyothi S. N.", "8": "Dr. Amudha J.", "9": "Dr. Chandrasekhar J.", "10": "Dr. Harini Jayaraman", "11": "Dr. Jayakumar M.", "12": "Dr. Jayaraj Poroor", "13": "Dr. Kumaraswamy G. N.", "14": "Dr. Latha Parameswaran", "15": "Dr. Manjula G. Nair", "16": "Dr. Mini K. M.", "17": "Dr. N. S. Murty", "18": "Dr. Nagaraja S. R.", "19": "Dr. Ramachandran T.", "20": "Dr. S. Ravishankar", "21": "Dr. Sindhu Thampatty K. C.", "22": "Dr. Somasundaram K.", "23": "Prof. Subba Rao R.", "24": "Dr. Sundararaman Gopalan", "25": "Dr. Thirumalini S.", "26": "Dr. B. L. Bhaskar", "27": "Deepthi Janardhan", "28": "Dr. B. Venkatesh", "29": "Ani R.", "30": "Dr. Bhagavathi Sivakumar P.", "31": "Dr. Gokulachandran J.", "32": "Dr. Jyothisha J. Nair", "33": "Dr. R. Karthikeyan", "34": "Mini Sujith", "35": "Dr. Nirmala Devi M.", "36": "M. V. Phanibhushana", "37": "Prashant R. Nair", "38": "Preetha P. K.", "39": "Dr. Purushothaman A.", "40": "Rajesh R.", "41": "Dr. N. Rakesh", "42": "Dr. T. K. Ramesh", "43": "Dr. Sriram Devanathan", "44": "Dr. Supriya P.", "45": "Dr. G. Jayachandran Nair", "46": "Dr. Madhav Datta", "47": "Srinivasan Raju", "48": "Dr. Ajith Kumar R.", "49": "Dr. Anand K. B.", "50": "Dr. Dhanesh G. Kurup", "51": "Dr. Elangovan M.", "52": "Dr. Ganesha Udupa", "53": "Prof. Gangadharan K.", "54": "Dr. Isha T. B.", "55": "Dr. Jayakumar J. S.", "56": "Dr. Jayanarayanan K.", "57": "Dr. Joshi C. Haran", "58": "Dr. Jyothi S. N.", "59": "Dr. M. R. Kaimal", "60": "Dr. Krishnashree Achuthan", "61": "Dr. (Col.) Kumar P. N.", "62": "Dr. Latha Parameswaran", "63": "Dr. Mahadevan S.", "64": "Dr. Murali Rangarajan", "65": "Dr. K. V. Nagaraja", "66": "Dr. Prema G.", "67": "Dr. Radhamani V. Pillay", "68": "Dr. Radhika N.", "69": "Rajkumar P. Sreedharan", "70": "Dr. Ramachandran T.", "71": "Dr. K. I. Ramachandran", "72": "Dr. Ramesh Kumar K.", "73": "Dr. Ravichandran J.", "74": "Dr. Saleeshya P. G.", "75": "Dr. Sankarprasad Bhuniya", "76": "Dr. Santhosh Kumar C.", "77": "Dr. Sasangan Ramanathan", "78": "Dr. Sasi K. K.", "79": "Dr. M. Sethumadhavan", "80": "Dr. Shailendhra K.", "81": "Dr. Shantanu Bhowmik", "82": "Dr. Soman K. P.", "83": "Dr. Somasundaram K.", "84": "Dr. Sriram Devanathan", "85": "Dr. Subhasri Duttagupta", "86": "Dr. Sundararaman Gopalan", "87": "Dr. Vidhya Balasubramanian", "88": "Dr. Ajith Ramesh", "89": "Dr. Anbuudayasankar S. P.", "90": "Dr. Bala Tripura Sundari B.", "91": "Dr. Balamurugan S.", "92": "Dr. Bhadrachalam Chitturi", "93": "Dr. Bhagavathi Sivakumar P.", "94": "Dr. Deepa Gopakumar O. S.", "95": "Dr. Deepa Gupta", "96": "Dr. Ganesh Neelakanta Iyer", "97": "Dr. Duraisamy Kumaresan", "98": "Dr. Geetha Senthilkumar", "99": "Dr. Ilangovan S.", "100": "Dr. Jayabarathi R.", "101": "Dr. Jeyakumar G.", "102": "Dr. Jyothisha J. Nair", "103": "Dr. P. Kanakasabapathy", "104": "Dr. R. Karthi", "105": "Dr. Kumaraswamy G. N.", "106": "Dr. Madhura Purnaprajna", "107": "Dr. Maya Mahajan", "108": "Dr. Meera Balachandran", "109": "Dr. Navin Kumar", "110": "Dr. Nikhil K. Kothurkar", "111": "Dr. Palanisamy T.", "112": "Dr. Prasanna Ramani", "113": "Prashant R. Nair", "114": "Dr. Prashanth Athri", "115": "Dr. Purushothaman A.", "116": "Dr. R. Sreekumar", "117": "Dr. Radhika N.", "118": "Dr. T. Rajagopalan", "119": "Dr. Rajathilagam B.", "120": "Dr. Rajni K. S.", "121": "Dr. Ramesh Bhakthavatchalu", "122": "Dr. M. Ramu", "123": "Dr. Rashmi M. R.", "124": "Dr. Ratna Kishore V.", "125": "Dr. Sabarinath Subramaniam", "126": "Dr. Saimurugan M.", "127": "Dr. Sajeev G. P.", "128": "Dr. K. Sangeeta Iyer", "129": "Dr. Sanjivi Arul", "130": "Dr. Satheesh Babu T. G.", "131": "Dr. Senthil Kumar T.", "132": "Dr. Shailendhra K.", "133": "Dr. Shunmuga Velayutham C.", "134": "Dr. Shyamala C. K.", "135": "Dr. Sindhu M. R.", "136": "Dr. Sivadas V.", "137": "Dr. Sivakumar M.", "138": "Dr. Sivakumar V.", "139": "Dr. Srikrishnan A. R.", "140": "Dr. Srinath R. Naidu", "141": "Dr. T. Srinivas Rao", "142": "Dr. Udaya Bhaskar Reddy Ragula", "143": "Dr. Veeresh Kumar G. B.", "144": "Dr. S.Veni", "145": "Dr. B. Venkatesh", "146": "Dr. Vijayakumari A.", "147": "Dr. Vivek Menon", "148": "Dr. Yamuna B.", "149": "Dr. Yamuna R.", "150": "Wg. Cdr. (Retd.) Sushil Kumar T. V. K.", "151": "Aarthi N.", "152": "Aarthi R.", "153": "Abirami K.", "154": "Adarsh S.", "155": "Dr. Ajay Kumara M. A.", "156": "Dr. Ajith Kumar S.", "157": "Akhil V. P.", "158": "Akila J.", "159": "Alok Kumar Jha", "160": "Ambika P.", "161": "Dr.  Amrita Thakur", "162": "Amritha S.", "163": "Ananta Sharma B. G.", "164": "Ananth Kumar M.", "165": "Dr. Anantha Narayanan V.", "166": "Dr. T. Ananthan", "167": "Angel T. S.", "168": "Anil Kumar S.", "169": "Dr. Anil Kumar Sharma", "170": "Anisha Radhakrishnan", "171": "Dr. Anita J. P.", "172": "Anjali B. S.", "173": "Anjana Jain", "174": "Dr. Anju Pillai S.", "175": "Ankusha Bandyopadhyay", "176": "Anu Chalil", "177": "Anu G. Kumar", "178": "Anudev J.", "179": "Anupa Vijay", "180": "Anuraj K", "181": "Anusha K. S.", "182": "Aravind Krishnan", "183": "Dr. Aravinth J.", "184": "Archana Devi R.", "185": "Archana K. Rajan", "186": "Archanaa R.", "187": "Arjun Bharadwaj", "188": "Dr. Arpita Thakre", "189": "Arun A.", "190": "Arun Rajendran", "191": "Arun Kumar C.", "192": "Arunkumar K.", "193": "Asha Ashok", "194": "Asha C. A.", "195": "Dr. Asha Sathish", "196": "Aswathy K. Nair", "197": "Dr. Athi Narayanan S.", "198": "Athul Shaji", "199": "Babu Namboothiri K.", "200": "Baby Sreeja S. D.", "201": "Bagyammal T.", "202": "Dr. Balajee Ramakrishnananda", "203": "Dr. Balaji K.", "204": "Balakrishnan P.", "205": "Basavaraj Noolvi", "206": "Baskar A.", "207": "S. Bhanu Prakash", "208": "Dr. Bharat Kishore Sharma", "209": "Bharath K. R.", "210": "Bharathi D.", "211": "Bhargavi R. Upadhyay", "212": "Bhavana V.", "213": "Bindu K. R.", "214": "Dr. Binoy B. Nair", "215": "Binu P. K.", "216": "Dr. Bipin Balaram", "217": "Dr. Biswambhar Rakshit", "218": "Boopalakrishnan S.", "219": "Boopathi T. S.", "220": "Chinmayi R.", "221": "Dayanand V.", "222": "Dr. K. Deepa", "223": "Deepak O. M.", "224": "Deepak Selvakumar R.", "225": "Deepakumari S.", "226": "Dr. Deepika Neela", "227": "Bri. Deepthi", "228": "Y. P. Deepthi", "229": "Devarajan K.", "230": "Devi S.", "231": "Devi Vijayan", "232": "Dhananjay Raghavan", "233": "Dhanya M. Dhanalakshmy", "234": "Dr. Dhanya N. M.", "235": "Dhanya Sathyan", "236": "Dileep B. P.", "237": "Dineshkumar L.", "238": "Divakar Shetty  A. S.", "239": "Divya R.", "240": "Divya Sharma S.G.", "241": "Dr. B Soundharajan", "242": "Dr. Rakesh Kumar", "243": "Dr. B. T. S. Ramanujam", "244": "Dr. S. Santhakumar", "245": "Dr. S. Giridhar Reddy", "246": "Dr. Selvakumar S.", "247": "Dr. Tripty Singh", "248": "Dr. Vanishri Bhat", "249": "Ebin P. S.", "250": "Dr. Elango K.", "251": "Dr. G. Saravana Prabu", "252": "Ganapathi Hedge", "253": "Gandhiraj R.", "254": "Ganesan M.", "255": "Dr. Gangadharan D.", "256": "Gayathri K.", "257": "Gayathri Narayanan", "258": "Gayathri V.", "259": "Geena Prasad", "260": "Geetha M.", "261": "Dr. J. Geetha", "262": "Dr. Geetha K. N.", "263": "Geethalekshmi V.", "264": "Geethu R. S.", "265": "Giriraja C. V.", "266": "Dr. Gopakumar G.", "267": "Govindarajan J.", "268": "Dr. Govindaraju M.", "269": "Dr. Gowtham R.", "270": "Greeshma Sarath", "271": "H. Manjunatha", "272": "Haridharan M. K.", "273": "Harikrishnan G.", "274": "Harikumar M. E.", "275": "Dr. Harini N.", "276": "Dr. Harish Ram D. S.", "277": "Dr. Ilango K.", "278": "Indu V.", "279": "Indulekha T. S.", "280": "Dr. J. Mahalakshmi", "281": "Dr. T. Jagadesh", "282": "N. Jaiganesh", "283": "Jalpa Shah", "284": "Janarthanan N.", "285": "Jasmine T. Bhaskar", "286": "Jayakumar M.", "287": "Jayakumar P.", "288": "Bri. Jayashree", "289": "Jayasree Narayanan", "290": "Jayasree M. Oli", "291": "Jayasree P. R.", "292": "Dr. Jeetu S. Babu", "293": "K. Jeeva Priya", "294": "Jevitha K. P.", "295": "Jeyanthi R.", "296": "Dr. Jinesh M. K.", "297": "Jisha R. C.", "298": "Jishnu Sankar V. C.", "299": "John Stanley", "300": "Jyotsna C", "301": "G. S. Jyotsna", "302": "Dr. K. S. Sreeranjini", "303": "Kamalaveni V.", "304": "Dr. Kannan M.", "305": "Dr. R. Kannan", "306": "Dr. Karthega M.", "307": "Dr. Karthi Balasubramanian", "308": "Karthick S.", "309": "Karthigha Balamurugan", "310": "Dr. Karthik V. Shankar", "311": "Karthika R.", "312": "Dr. Kaustav Bhowmick", "313": "Kavitha C. R.", "314": "Dr. Kavitha D.", "315": "Kavitha K. R.", "316": "Kavitha N. Pillai", "317": "Kayalvizhi N.", "318": "Dr. V. Kesavulu Naidu", "319": "Dr. Kirthiga S.", "320": "V. S. Kirthika Devi", "321": "Kirthika N.", "322": "Kirti S. Pande", "323": "Dr. Kiruthika S.", "324": "Dr. Krishna Kumar P.", "325": "Krishna Prakash N.", "326": "Dr. Krishna Prasad R.", "327": "Dr. Kumar Abhishek", "328": "Lakshmi Mohan", "329": "Lakshmikanthan C.", "330": "Lalith Prakash E.", "331": "S. Lalitha", "332": "Dr. Lalithamani N.", "333": "Lata Lachu Wadhwani", "334": "Latha", "335": "Dr. Lavanya R.", "336": "Dr. Laxman Vaitla", "337": "Lekha S. Nair", "338": "Lekshmi R. Chandran", "339": "Lekshmi R. R.", "340": "Lekshmi S.", "341": "Lekshmi S. Nair", "342": "Dr. M. Dharani", "343": "M. Vamsee Krishna Kiran", "344": "Dr. Madhu Mohan N.", "345": "Mahadevan Lakshmanan", "346": "R. Mahalakshmi", "347": "Mahendra Naktuji Nadanwar", "348": "Malathi P.", "349": "Mamatha I.", "350": "Mamatha T. M.", "351": "Manitha P. V.", "352": "Manju Venugopalan", "353": "Manjusha Nair", "354": "Manjusha R.", "355": "Dr. Manoj Kumar Panda", "356": "Manu Sivan", "357": "Dr. P. Maran", "358": "Dr. Maroju Prashanth", "359": "Maya P.", "360": "Meena Belwal", "361": "Dr. K. N. Meera", "362": "Meher Madhu Dharmana", "363": "Mekaladevi V.", "364": "Mini Sujith", "365": "Dr. Mithun Mohan", "366": "Mohan Kumar S.", "367": "Dr. T. M. Mohan Kumar", "368": "Mohankumar N.", "369": "Dr. T. Mohanraj", "370": "Mohanrajan S. R.", "371": "Mrudula Prashanth", "372": "Dr. K. Murali", "373": "Dr. Murali Krishna P.", "374": "Dr. Murugadass K.", "375": "Nalinadevi K.", "376": "Nalini S.", "377": "Dr. A. K. Nanda Kumar", "378": "Nandagopal J. L.", "379": "Nandhini I.", "380": "Nandi Vardhan H. R.", "381": "B. H. Nanjundareddy", "382": "Nanthakumar P.", "383": "Dr. Natarajamani S.", "384": "Naveen Bhat", "385": "Navya Mohan", "386": "N. Neelima", "387": "Neeta Mishra", "388": "Dr. Neetu Srivastava", "389": "Nidhi Gangrade", "390": "Nippun Kumaar A. A.", "391": "Nithya K.", "392": "M. Nithya", "393": "Dr. Oruganti Venkata Ramana Murthy", "394": "P. Suresh Kumar", "395": "Padmamala Sriram", "396": "Dr. Padmanaban R.", "397": "Dr. Padmavathi S.", "398": "Dr. Paramanathan P.", "399": "Pargunarajan K.", "400": "Parvathy G.", "401": "Parvathy S.", "402": "Peeyush K. P.", "403": "Dr. Poongothai N.", "404": "Poorna S. S.", "405": "Poornima Mohan", "406": "Poornima V.", "407": "Prabha G.", "408": "Prabhu E.", "409": "Prabhu S.", "410": "Prabhu T.", "411": "Prabhudev B. M.", "412": "Dr. Pradeep S. Jakkareddy", "413": "Dr. V. Pragadeeswarar", "414": "Prakash A. S.", "415": "Prakash C.", "416": "Dr. Prakash G.", "417": "Prakash Marimuthu K.", "418": "Dr. Prakash P.", "419": "P. Prakash", "420": "Pramod Kumar", "421": "R. Pramod", "422": "Pramod Sreedharan", "423": "Prasanna Vadana D.", "424": "Prasanth M. Warrier", "425": "Prashanth B. N.", "426": "Prathibha S. Babu", "427": "Prathibhamol C. P.", "428": "Prathilothamai M.", "429": "Dr. D. Praveen", "430": "Praveen I.", "431": "Bri. Praveena", "432": "Praveenkumar N.", "433": "Preetha P. K.", "434": "Dr. Prema P.", "435": "Priya B. K.", "436": "Priya Harikumar", "437": "Dr. Priya M. G.", "438": "Dr. Priyanka Kumar", "439": "Priyanka Vivek", "440": "Priyatharishini M.", "441": "Pushparajan M.", "442": "Dr. Puvaneshwari P.", "443": "R. Ramkrishnan", "444": "Radha D.", "445": "Dr. Radha Iyer R.", "446": "G. Radhakrishnan", "447": "Radhika G.", "448": "Raghavendra Ravikiran K.", "449": "Raghesh Krishnan K.", "450": "Raghu J. (Mandya)", "451": "Dr. Raghuram P.", "452": "Rahul Lal P.", "453": "Dr. Rahul Sharma K.", "454": "Rahulan N", "455": "Dr. Rajakumar Arul", "456": "Rajasree S. R.", "457": "Dr. Rajath Vasudevamurthy", "458": "Rajeevlochana G. Chittawadigi", "459": "Rajesh C. B.", "460": "Rajesh M.", "461": "Dr. Rajesh Kannan Megalingam", "462": "Rajesh R.", "463": "Rajesh Senthil Kumar T.", "464": "Rajesh V. R.", "465": "Rajeswari P.", "466": "Raji Ramachandran", "467": "Rakesh N.", "468": "Rakesh P.", "469": "Dr. Ramanathan R.", "470": "Dr. S. Ramasubramanian", "471": "Ramesh S. R.", "472": "Dr. J. Ramprabhakar", "473": "Ramya G. R.", "474": "Ramya R.", "475": "Ramya U. M.", "476": "Ranjith R.", "477": "Rasana Nanoth", "478": "Ravi Kumar V.", "479": "Ravikumar S.", "480": "Bri. Remya", "481": "Remya Rajesh", "482": "Resmi R.", "483": "Ritwik M.", "484": "Rolant Gini J.", "485": "Sabarish B. A.", "486": "Sabarish Narayanan B.", "487": "Sagar B.", "488": "V. Sailaja", "489": "Saisuriyaa G.", "490": "Dr. Sakthivel N. R.", "491": "Sakthivel R.", "492": "Sambhu R.", "493": "Sampath Kumar S.", "494": "Sandeep Koundinya", "495": "Sandhya Harikumar", "496": "Sandhya V.", "497": "Sangita Khare", "498": "R. V. Sanjika Devi", "499": "Dr. Santhosh B.", "500": "Dr. Sarada Jayan", "501": "Sarath R. S.", "502": "Sarath S.", "503": "Sarath T. V.", "504": "Dr. Saravana Murugan S.", "505": "Saravanan R.", "506": "S. Saravanan", "507": "Sasikala T", "508": "Sathishkumar V. R.", "509": "Sathiya R. R.", "510": "P. Satish Kumar", "511": "Dr. Satyajith K. T.", "512": "Seema P. N.", "513": "C. Selvi", "514": "Senthil Murugan", "515": "Senthilkumar D.", "516": "Dr. Senthilkumar M.", "517": "Shali S.", "518": "Dr. Shankar S.", "519": "Dr. Shankara", "520": "Shanmuga Priya S.", "521": "Shanmugasundaram A.", "522": "Dr. Shanmugha Sundaram G. A.", "523": "Shanmugha Sundaram R.", "524": "Shashi Kumar M. E.", "525": "Shekhar G.", "526": "Shiju Sathyadevan", "527": "Shivapratap Gopakumar", "528": "Shobana K.", "529": "Dr. Shriram K. Vasudevan", "530": "Siji Rani S.", "531": "Sikha O. K.", "532": "Simi S.", "533": "Sindhu S.", "534": "Sini Raj P.", "535": "K. Sireesha", "536": "Sivanesan M.", "537": "K. Sivaselvi", "538": "Dr. Sivasubramanian G.", "539": "Sivraj P.", "540": "Smita Sail", "541": "Smita Singh", "542": "Sonali Agrawal", "543": "Dr. Sophi Shilpa G.", "544": "Sreebha Bhaskaran", "545": "Dr. Sreedevi K. Menon", "546": "Sreeja Kochuvila", "547": "Sreejith Kailas T.", "548": "Dr. Sreekanth K. M.", "549": "Dr. Sreekanth V.", "550": "Sreekumar P. C.", "551": "Sreelekshmi R. S.", "552": "Dr. Sreevalsa Kolathyar", "553": "Srihari S.", "554": "Srikanth V.", "555": "Dr. Sripad H. Ghaligi", "556": "Dr. Sriram Sankaran", "557": "Sruthy S.", "558": "Sruthy V.", "559": "Subash Moorthy R.", "560": "Subathra P.", "561": "S. Subbulakshmi", "562": "Dr. Subeesh T.", "563": "Suchithra M.", "564": "Sudakshina Bhattacharyya", "565": "Sudha Yadav", "566": "Sudheesh P.", "567": "Suguna G.", "568": "Dr. Suja P.", "569": "Sujee R.", "570": "Dr. Sukanta Nayak", "571": "Dr. Sulagna Mohanty", "572": "Dr. Sumathi I. R.", "573": "Sumathi N.", "574": "Sumesh A.", "575": "Sumesh A. K.", "576": "Sumesh C. S.", "577": "Dr. Suneesh P. V.", "578": "Sunil Nag P. V.", "579": "R. Sunitha", "580": "Dr. Supriya M.", "581": "Surya M.", "582": "Suyampu Lingam A.", "583": "Swaminadhan R.", "584": "Swaminathan J.", "585": "Dr. Swapna T. R.", "586": "Dr. Swarnalatha V.", "587": "Syama S.", "588": "Dr. P. Tamilalagan", "589": "Tamilarasan N.", "590": "Teena V.", "591": "Dr. Thangavelu S.", "592": "Thara S.", "593": "Thenarasu M.", "594": "Dr. Thilagavathy P.", "595": "Ulhas K. Annigeri", "596": "Ullas S", "597": "B. Uma Maheswari", "598": "Dr. Umamaheswari A.", "599": "Unnikrishnan D.", "600": "Dr. Upadyayula K. V. Sarma", "601": "V. Priya Darshini", "602": "Dr. V. Ravikumar Pandi", "603": "Dr. Vanitha V.", "604": "Vasanth Kumar G.", "605": "Vasundhara T", "606": "Veena G.", "607": "Dr. Venkata Ravi Kumar Darbha", "608": "K. N. Venkatachalaiah", "609": "Dr. Venkataraman D.", "610": "Vidhya S.", "611": "Vidya L.", "612": "Vignesh V.", "613": "Dr. Vijaya Chandrakala K. R. M.", "614": "Vijith K.", "615": "Dr. Vikas Rajan", "616": "Vineetha Jain", "617": "Vinitha Panicker", "618": "Vinod Kotebavi", "619": "M. Vinodhini", "620": "Dr. Vinodkumar A.", "621": "Vinoj Vasu", "622": "Vipin V.", "623": "S. Vishnu Rajendran", "624": "Vishwas H. N.", "625": "Dr. Viswas S. Nair", "626": "Vivek A.", "627": "Asish", "628": "Bri. Dhivvya", "629": "Krishna Prasad", "630": "Bri. Neetha Joseph", "631": "Rupesh", "632": "Bri. Ruphiny", "633": "Santhana Lakshmi S.", "634": "Bri. Seena", "635": "Sekhar Milan", "636": "Bri. Shakunthala", "637": "SREEVIDYA B.", "638": "Sumesh K. J.", "639": "K. N. Surendran", "640": "V. Swapna", "641": "Bri. Vineetha", "642": "Anu Prabha R. S.", "643": "Devanathan B.", "644": "S. Geetha", "645": "Krishna S.", "646": "Prasad M.", "647": "Rahul Varma U.", "648": "Sonu P.", "649": "Srinivaas A.", "650": "Thushara M. G.", "651": "Manikantan", "652": "P. G. Sivakumar", "653": "Jose James"}